LICENSE
pythogen/__init__.py
pythogen/console.py
pythogen/exceptions.py
pythogen/main.py
pythogen/models.py
pythogen/packager.py
pythogen/parsers/__init__.py
pythogen/parsers/constants.py
pythogen/parsers/document.py
pythogen/parsers/inline_schemas_aggregator.py
pythogen/parsers/operations.py
pythogen/parsers/parameters.py
pythogen/parsers/paths.py
pythogen/parsers/references.py
pythogen/parsers/request_body.py
pythogen/parsers/response.py
pythogen/parsers/schemas.py
pythogen/renderer.py
pythogen/settings.py
pythogen/templates/http_client/main.j2
pythogen/templates/http_client/method.j2
pythogen/templates/http_client/operation_params_schemas.j2
pythogen/templates/http_client/request-metrics.j2
pythogen/templates/http_client_package/init-py.j2
pythogen/templates/http_client_package/pyproject-toml.j2
pythogen-0.2.41.dist-info/LICENSE
pythogen-0.2.41.dist-info/METADATA
pythogen-0.2.41.dist-info/WHEEL
pythogen-0.2.41.dist-info/entry_points.txt
pythogen-0.2.41.dist-info/RECORD
