Metadata-Version: 2.1
Name: pythogen
Version: 0.2.41
Summary: Generator of python HTTP-clients from OpenApi specification.
Home-page: https://github.com/artsmolin/pythogen
License: MIT
Keywords: openapi,openapi-generator,swagger,http-client,generator
Author: Artur Smolin
Author-email: artursmolin@outlook.com
Requires-Python: >=3.10,<4.0
Classifier: Development Status :: 4 - Beta
Classifier: Environment :: Console
Classifier: Intended Audience :: Developers
Classifier: License :: OSI Approved :: MIT License
Classifier: Natural Language :: English
Classifier: Operating System :: OS Independent
Classifier: Programming Language :: Python :: 3
Classifier: Programming Language :: Python :: 3.10
Classifier: Programming Language :: Python :: 3.11
Classifier: Programming Language :: Python :: 3.12
Classifier: Topic :: Software Development :: Code Generators
Classifier: Topic :: Utilities
Classifier: Typing :: Typed
Requires-Dist: autoflake (>=2.2.0,<3.0.0)
Requires-Dist: black (>=23.3.0,<24.0.0)
Requires-Dist: inflection (>=0.5.1,<0.6.0)
Requires-Dist: isort (>=5.12.0,<6.0.0)
Requires-Dist: jinja2 (>=3.1.1,<4.0.0)
Requires-Dist: openapi-spec-validator (>=0.7.1,<0.8.0)
Requires-Dist: pydantic (>=2.0.2,<3.0.0)
Requires-Dist: pytest-cov (>=4.1.0,<5.0.0)
Requires-Dist: pyyaml (>=6.0.1,<7.0.0)
Requires-Dist: typer (>=0.9.0,<0.10.0)
Project-URL: Repository, https://github.com/artsmolin/pythogen
